eol_timeline/__init__.py
eol_timeline/cli.py
eol_timeline/data_parser.py
eol_timeline/eol_resolver.py
eol_timeline/file_scanner.py
eol_timeline/main.py
eol_timeline/models.py
eol_timeline/presenter.py
eol_timeline-0.1.0.dist-info/METADATA
eol_timeline-0.1.0.dist-info/WHEEL
eol_timeline-0.1.0.dist-info/entry_points.txt
eol_timeline-0.1.0.dist-info/top_level.txt
eol_timeline-0.1.0.dist-info/RECORD
